Workbook

Sheet Rendimiento SGSI
A1: RENDIMIENTO SGSI

Sheet Dashboard SGSI
A1: ID Medición | B1: Descripción de medición | C1: Ciclo PDCA | D1: ¿En qué proceso SGSI se encuentra? | E1: Método y/o recursos | F1: Objetivo de medición | G1: Responsable de obtener el cálculo | H1: Periodo de actualización de cálculo | I1: Indicador | J1: Cálculo actual | K1: ¿Cumple? | L1: Planes de acción recomendados
A2: 1 | B2: Porcentaje de OESIs alineados a los OEEs | C2: P | D2: Alineamiento de Objetivos de Seguridad de la Información y Objetivos Estratégicos de la Empresa | E2: Revisar la Matriz OEE vs OSI y verificar la fórmula de calificación que se aplicará a cada OSI. | F2: Determinar cuantos OSIs (Objetivos de Seguridad de la Información) se encuentran alineados en base al apoyo que brindan a los OEEs (Objetivos Estratégicos Empresariales). | G2: Gerente General | H2: Cada 12 meses | I2: >= 85 % | J2: ='Matriz OEE vs OSI'!C22 -> 86.538462 | K2: =IF(J2<>"",IF(J2>=85,"SI","NO"),"NO") -> SI | L2: Analizar las estrategias empresariales para realizar los ajustes correspondientes respecto a los OEEs. Analizar las estrategias de Seguridad de la Información para realizar los ajustes correspondientes respecto a los OSI.
A3: 4 | B3: Porcentaje de presupuesto cubierto por los costos de SGSI, según lo que se haya avanzado en el año | C3: C | D3: Evaluación de Riesgos de Seguridad de la Información | E3: Rastrear el gasto en procesos de gestión de riesgos de TI. El dato se puede obtener de los datos financieros que gestiona el área de Gerencia General. | F3: Determinar si se planifica el presupuesto asignado para el SGSI | G3: Gerente General | H3: Cada 12 meses | I3: <= 100 % | J3: 0.99 | K3: =IF(J3<=100,"SI","NO") -> SI | L3: Analizar si la eficiencia y efectividad del SGSI ameritan en aumentar o ajustar el presupuesto asignado para el siguiente periodo.
A4: 5 | B4: Número de sucesos de indisponibilidad del Sistema SIEMPRESOFT ERP. | C4: C | D4: Evaluación de Riesgos de Seguridad de la Información | E4: Revisar y contar los reportes de incidentes donde se demuestre que el Sistema SIEMPRESOFT ERP haya quedado indisponible. | F4: Determinar la efectividad del SGSI en la operatividad de uno de los servicios más importante de SIEMPRESOFT por no seguir los documentos establecidos (políticas, procedimientos, estándares o instructivos) | G4: Oficial de Seguridad de la Información | H4: Cada 12 meses | I4: <= 3 | J4: 1 | K4: =IF(J4<>"",IF(J4<=6,"SI","NO"),"NO") -> SI | L4: Analizar si la documentación pertinente está manifestando ambigüedades en la operatividad del SGSI. Analizar si hay riesgos nuevos no cubiertos en la evaluación de riesgos.
A5: 5 | B5: Número de sucesos de indisponibilidad del Servicio SIEMPRESOFT OSE. | C5: C | D5: Evaluación de Riesgos de Seguridad de la Información | E5: Revisar y contar los reportes de incidentes donde se demuestre que el Servicio SIEMPRESOFT OSE haya quedado indisponible. | F5: Determinar la efectividad del SGSI en la operatividad de los servicios más importante de SIEMPRESOFT por no seguir los documentos establecidos (políticas, procedimientos, estándares o instructivos) | G5: Oficial de Seguridad de la Información | H5: Cada 12 meses | I5: <=3 | J5: 1 | K5: =IF(J5<>"",IF(J5<=6,"SI","NO"),"NO") -> SI | L5: Analizar si la documentación pertinente está manifestando ambigüedades en la operatividad del SGSI. Analizar si hay riesgos nuevos no cubiertos en la evaluación de riesgos.
A6: 8 | B6: Promedio total de los colaboradores en todas las notas de los examenes de evaluación interna de comprensión de los documentos del SGSI | C6: C | D6: Concienciación | E6: Revisar todos los exámenes brindados en la frecuencia establecida y promediar todas las notas de todos los colaboradores y obtener un promedio total en general para SIEMPRESOFT. | F6: Determinar la efectividad de los cursos o charlas impartidas o gestionadas por SIEMPRESOFT respecto a reforzar conocimientos de Seguridad de la Información. | G6: Oficial de Seguridad de la Información | H6: Cada 12 meses | I6: >= 14 | J6: 19 | K6: =IF(J6<>"",IF(J6>=14,"SI","NO"),"NO") -> SI | L6: Analizar si están siendo efectivos los métodos de enseñanza o capacitación dentro del plan de capacitación. Evaluar a los participantes y consultar sus puntos de vista respecto a los contenidos impartidos.
A7: 11 | B7: Tasa de Incidentes de Seguridad por Módulo del ERP y Análisis de Causas | C7: C | D7: Revisión por la Alta Dirección | E7: Numero de eventos e incidentes por módulo del ERP, Registros de incidentes SGSI, indicadores de las causas de incidentes | F7: Identificar los procesos (módulos) del ERP que presentan mayor concentración de incidentes y sus causas principales, para mejorar la disponibilidad, continuidad y seguridad del servicio ofrecido como PSE/OSE y fortalecer la toma de decisiones de la Dirección. | G7: Oficial de Seguridad de la Información | H7: Cada 12 meses | I7: <= 10% | J7: =531/1800*1 -> 0.295 | K7: =IF(J7<>"",IF(J7>=1,"SI","NO"),"NO") -> NO | L7: Reducir los incidentes recurrentes y las actualizaciones por base de datos
B8: incorporar nuevos indicadores de medición por área marco ITIL | J8: SI | K8: =COUNTIF(K2:K7,"SI") -> 5
B9: incorporar indicadores de los controles del anexoa | J9: NO | K9: =COUNTIF(K2:K7,"NO") -> 1

Sheet Rendimiento OESI
A1: RENDIMIENTO OBJETIVOS DE SGSI

Sheet Dashboard OESI
A1: ID Medición | B1: Descripción de medición | C1: Método y/o recursos | D1: Responsable de obtener el cálculo | E1: Periodo del cálculo | F1: Indicador | G1: Cálculo actual | H1: ¿Cumple? | I1: ¿Cumple? | J1: Cantidad | K1: %
A2: 1 | B2: Disminuir la cantidad de incidentes en un 30% en el servicio Siempresoft ERP en los próximos 12 meses. | C2: Revisar la cantidad de incidentes informados relacionados al Sistema SIEMPRESOFT ERP, comparado del total de incidentes al final de cada año. | D2: Jefe de soporte al cliente | E2: Mensual | F2: >= 30% | G2: 0.0066 | H2: =IF(G2>=F2,"Si","No") -> No | I2: SI | J2: =COUNTIF(H2:H10,"SI") -> 5 | K2: =J2/J4 -> 0.55555556
A3: 2 | B3: Permanecer en el Registro de Proveedor de Servicios Electrónicos (PSE) con porcentaje de constancias de recepción rechazadas menor al 2% en un año por cliente. | C3: Revisar las respuestas de SUNAT y contabilizar y calcular el porcentaje de las rechazadas en comparación del total. | D3: Asistente de Producción | E3: Cada 3 meses | F3: <= 2 % | G3: 0.00073 | H3: =IF(G3<="2","Si","No") -> Si | I3: NO | J3: =COUNTIF(H2:H10,"NO") -> 4 | K3: =J3/J4 -> 0.44444444
A4: 3 | B4: Migrar más del 70% de clientes a la nueva arquitectura de Plataforma como Servicio en los próximos 12 meses. | C4: Incrementa la cantidad de ambientes migrados a la plataforma del ERP PaaS en cada mes. | D4: Asistente de Producción | E4: Cada 3 meses | F4: >= 70% | G4: 0.0011 | H4: =IF(G4>=70,"Si","No") -> No | J4: =SUM(J2:J3) -> 9 | K4: =SUM(K2:K3) -> 1
A5: 4 | B5: Permanecer en el Registro de Operadores de Servicios Electrónicos cumpliendo con el Listado de Requisitos y Obligaciones del OSE. | C5: Verificar el cumplimiento de las obligaciones que debe cumplir el OSE. Revisar la cantidad de incumplimientos en el año. | D5: Oficial de seguridad de la información | E5: Cada 3 meses | F5: = 100% | G5: 1 | H5: Si
A6: 5 | B6: Mejorar la puntuación de seguridad en los servicios de la nube, debe ser mayor al 75%. | C6: Incrementar el porcentaje de las recomendaciones de puntuación segura en los servicios en la nube comparado con el anterior | D6: Jefe de Producción | E6: Cada 6 meses | F6: >= 75% | G6: 0.89 | H6: Si
A7: 6 | B7: Mejorar la puntuación de seguridad de los dispositivos endpoint, debe ser mayor al 75%. | C7: Incrementar el porcentaje de las recomendaciones de seguridad para los puntos de conexión. | D7: Jefe de Producción | E7: Cada 6 meses | F7: >=75% | G7: 0.73 | H7: =IF(G7>=75%, "Si","No") -> No
A8: 7 | B8: Obtener un SLA de 99% de nuestros servicios en la nube (ERP). | C8: Contabilizar la cantidad de veces y el tiempo (horas) de respuesta ante la indisponibilidad de los servicios de Siempresoft (ERP). | D8: Asistente de Producción | E8: Cada 3 meses | F8: < 86.40 | G8: 2.13 | H8: =IF(G8<86.4,"Si","No") -> Si
A9: 8 | B9: Mantener una disponibilidad del servicio ose en un 99.97%. | C9: Revisar la cantidad de veces y el tiempo (horas) que el sistema para validación de comprobantes OSE no está disponible (registro de incidencias) | D9: Responsable de Plataforma OSE | E9: Cada 3 meses | F9: < 2.59 | G9: 2.13 | H9: =IF(G9<2.59,"Si","No") -> Si
A10: 9 | B10: Implementar DevOps en los procesos de desarrollo y despliegue en un nivel de madurez adecuado para la empresa. | C10: Implementar DevOps y garantizar el Level 3 aunque sea en unos de los Proyectos de Siempresoft al finalizar el año. | D10: Jefe de Desarrollo | E10: Cada 6 meses | F10: >= 1 | G10: 0 | H10: =IF(G10>=1,"Si","No") -> No

Sheet Matriz OEE vs OSI
A1: Matriz de los Objetivos Estratégicos de la Empresa vs Objetivos Estratégicos de Seguridad de la Información
A2: OEE \ OSI | C2: OESI1 | D2: OESI2 | E2: OESI3 | F2: OESI4 | G2: OESI5 | H2: OESI6 | I2: OESI7 | J2: OESI8 | K2: OESI9
C3: ='Dashboard OESI'!B2 -> Disminuir la cantidad de incidentes en un 30% en el servicio Siempresoft ERP en los próximos 12 meses. | D3: ='Dashboard OESI'!B3 -> Permanecer en el Registro de Proveedor de Servicios Electrónicos (PSE) con porcentaje de constancias de recepción rechazadas menor al 2% en un año por cliente. | E3: ='Dashboard OESI'!B4 -> Migrar más del 70% de clientes a la nueva arquitectura de Plataforma como Servicio en los próximos 12 meses. | F3: ='Dashboard OESI'!B5 -> Permanecer en el Registro de Operadores de Servicios Electrónicos cumpliendo con el Listado de Requisitos y Obligaciones del OSE. | G3: ='Dashboard OESI'!B6 -> Mejorar la puntuación de seguridad en los servicios de la nube, debe ser mayor al 75%. | H3: ='Dashboard OESI'!B7 -> Mejorar la puntuación de seguridad de los dispositivos endpoint, debe ser mayor al 75%. | I3: ='Dashboard OESI'!B8 -> Obtener un SLA de 99% de nuestros servicios en la nube (ERP). | J3: ='Dashboard OESI'!B9 -> Mantener una disponibilidad del servicio ose en un 99.97%. | K3: ='Dashboard OESI'!B10 -> Implementar DevOps en los procesos de desarrollo y despliegue en un nivel de madurez adecuado para la empresa.
A4: OEE1 | B4: Implementación del área de Marketing para publicitar servicios y mejora de imagen corporativa. | C4: P | D4: S | I4: S | J4: S
A5: OEE2 | B5: Fidelizar a clientes a través de la administración del éxito del cliente (SCM), reducir tasa de abandono a 2%. | C5: S | E5: S | I5: S | J5: S | K5: S
A6: OEE3 | B6: Crear agentes de IA para automatizar ciertos procesos del ERP. Crear un mínimo de 3 agentes. | I6: S
A7: OEE4 | B7: Mejorar el área de Soporte al cliente mediante el uso de IA como Chatbot y agentes de voz que permitirá reducir tiempos de respuesta y disponibilidad de atención básica 24/7. | I7: S
A8: OEE5 | B8: Retener el talento a través de mejoras en condiciones laborales y capacitación. | C8: S | E8: S | G8: S | H8: S | I8: S | J8: S | K8: S
A9: OEE6 | B9: Implementar crecimiento guiado por el producto. | C9: S | D9: S | E9: S | F9: S | J9: S | K9: S
A10: OEE7 | B10: Automatizar la entrega de nuevas versiones del ERP, reduciendo tiempo de pruebas y el uso de tecnologías de entrega continua. | C10: S | D10: S | E10: S | F10: S | I10: S | K10: P
A11: OEE8 | B11: Hacer escalable el ERP sin depender de infraestructura, trasladando mayor responsabilidad al proveedor de la nube. | C11: S | D11: S | E11: S | F11: S | I11: P | J11: P | K11: S
B13: Leyenda | C13: Valor | D13: Puntuación | I13: Descripción | J13: Valor mínimo | K13: Obtenido
B14: P = Primario | Puede existir máximo un primario por OSI según los OEE | Equivale a 3 puntos | C14: 3 | D14: =COUNTIF(C4:K11,"P") -> 4 | I14: Evaluación de alineamiento de OSI con los OEEs. | J14: =(9*C14)+(25*C15) -> 52 | K14: =(C14*D14)+(C15*D15) -> 45
B15: S = Secundario | No se exige mínimo ni máximo | Equivale a 1 punto | C15: 1 | D15: =COUNTIF(C4:K11,"S") -> 33
B17: PUNTAJE | C17: =(COUNTIF(C4:C11,"S")*$C$15)+(COUNTIF(C4:C11,"P")*$C$14) -> 8 | D17: =(COUNTIF(D4:D11,"S")*$C$15)+(COUNTIF(D4:D11,"P")*$C$14) -> 4 | E17: =(COUNTIF(E4:E11,"S")*$C$15)+(COUNTIF(E4:E11,"P")*$C$14) -> 5 | F17: =(COUNTIF(F4:F11,"S")*$C$15)+(COUNTIF(F4:F11,"P")*$C$14) -> 3 | G17: =(COUNTIF(G4:G11,"S")*$C$15)+(COUNTIF(G4:G11,"P")*$C$14) -> 1 | H17: =(COUNTIF(H4:H11,"S")*$C$15)+(COUNTIF(H4:H11,"P")*$C$14) -> 1 | I17: =(COUNTIF(I4:I11,"S")*$C$15)+(COUNTIF(I4:I11,"P")*$C$14) -> 9 | J17: =(COUNTIF(J4:J11,"S")*$C$15)+(COUNTIF(J4:J11,"P")*$C$14) -> 7 | K17: =(COUNTIF(K4:K11,"S")*$C$15)+(COUNTIF(K4:K11,"P")*$C$14) -> 7
B19: Evaluación TOTAL
B20: Mínimo esperado | C20: =J14 -> 52
B21: Obtenido | C21: =SUM(C17:K17) -> 45
B22: % Representación | C22: =C21*100/C20 -> 86.538462

Sheet Matriz EPI vs OSI
A1: Matriz de las Expectativas de la Partes Interesadas vs Objetivos de Seguridad de la Información
A2: EPI \ OSI | C2: OESI1 | D2: OESI2 | E2: OESI3 | F2: OESI4 | G2: OESI5 | H2: OESI6 | I2: OESI7 | J2: OESI8 | K2: OESI9
C3: ='Dashboard OESI'!B2 -> Disminuir la cantidad de incidentes en un 30% en el servicio Siempresoft ERP en los próximos 12 meses. | D3: ='Dashboard OESI'!B3 -> Permanecer en el Registro de Proveedor de Servicios Electrónicos (PSE) con porcentaje de constancias de recepción rechazadas menor al 2% en un año por cliente. | E3: ='Dashboard OESI'!B4 -> Migrar más del 70% de clientes a la nueva arquitectura de Plataforma como Servicio en los próximos 12 meses. | F3: ='Dashboard OESI'!B5 -> Permanecer en el Registro de Operadores de Servicios Electrónicos cumpliendo con el Listado de Requisitos y Obligaciones del OSE. | G3: ='Dashboard OESI'!B6 -> Mejorar la puntuación de seguridad en los servicios de la nube, debe ser mayor al 75%. | H3: ='Dashboard OESI'!B7 -> Mejorar la puntuación de seguridad de los dispositivos endpoint, debe ser mayor al 75%. | I3: ='Dashboard OESI'!B8 -> Obtener un SLA de 99% de nuestros servicios en la nube (ERP). | J3: ='Dashboard OESI'!B9 -> Mantener una disponibilidad del servicio ose en un 99.97%. | K3: ='Dashboard OESI'!B10 -> Implementar DevOps en los procesos de desarrollo y despliegue en un nivel de madurez adecuado para la empresa.
A4: Clientes | B4: Que los servicios brindados por SIEMPRESOFT generen valor agregado para su negocio a través de un sistema SEGURO con la información disponible, íntegra y confidencial. | C4: P | D4: S | E4: S | F4: S | G4: S | I4: P | J4: S | K4: S
B5: Que los servicios cubran los acuerdos contractuales respetando los contratos establecidos. | C5: S | D5: S | E5: S | G5: S | I5: S | J5: S | K5: S
A6: Entidades gubernamentales | B6: Que los servicios informáticos que brinda SIEMPRESOFT a los contribuyentes respecto a Facturación Electrónica, cumplan con la LEY DE PROTECCIÓN DE DATOS PERSONALES entre otras leyes y regulaciones. | C6: S | D6: S | E6: S | F6: S | G6: S | H6: S | K6: S
A7: SUNAT | B7: Que los servicios informáticos que brinda SIEMPRESOFT a los contribuyentes respecto a Facturación Electrónica y validación de comprobantes, cumplan con las resoluciones emitidas para la Seguridad de la Información. | D7: S | E7: S | F7: S | I7: S | J7: P | K7: S
B8: Que la empresa se certifique y mantenga la norma ISO 27001. | D8: P | F8: P
A9: Dueño de la empresa | B9: Que el Sistema de Gestión de Seguridad de la Información sea efectivo para apoyar a la toma de decisiones y lograr el éxito de los objetivos estratégicos. | C9: S | D9: S | F9: S | G9: S | H9: S | I9: S | J9: S
B10: Que el Sistema de Gestión de Seguridad de la Información genere valor financiero a SIEMPRESOFT para obtener el Retorno de Inversión. | D10: S | F10: S | K10: S
A11: Colaboradores | B11: Que el Sistema de Gestión de Seguridad de la Información sea entendible y fácil de ejecutar para lograr el cumplimiento con las políticas y documentos que la comprenden. | G11: S | H11: S
B12: Que exista capacitación constante para actualizar los conocimientos necesarios para cumplir con el SGSI. | C12: S | D12: S | F12: S | K12: S
B13: Que las condiciones de continuidad de seguridad de la información estén planificadas con el objetivo de cumplir con el SGSI ante una situación de desastre. | I13: S | J13: S
A14: Proveedores y socios | B14: Que las alianzas contractuales cubran la protección de información sensible de una forma segura y eficaz. | D14: S | F14: S | G14: S | H14: S
A15: Micrsoft Azure | B15: Que la integración de la Plataforma Azure en el Sistema de Gestión de Seguridad de la Información mantenga la solidez respecto a la confidencialidad y disponibilidad de los servicios. | D15: S | E15: S | F15: S | G15: S | H15: S | I15: S | J15: S | K15: S
A16: Microsoft Office | B16: Que los datos de los usuarios estén asegurados y proteja los dispositivos de ataques y amenazas de seguridad. | E16: S | G16: P | H16: P | K16: S
A17: Auditores externos | B17: Que SIEMPRESOFT esté manteniendo eficientemente la evolución del SGSI según el cumplimiento normativo. | D17: S | F17: S
A18: INDECI | B18: Que SIEMPRESOFT cumpla con los requisitos mínimos de seguridad física en los ambientes de trabajo. | D18: S | F18: S
A19: Proveedores de Servicios Electrónicos | B19: Que el servicio cubra con los acuerdos contractuales para evitar incumplimientos tributarios y sanciones legales con SUNAT. | D19: S | E19: S | F19: S | I19: S | J19: S
A20: Competidores | B20: Que la competencia impulse a mejorar los productos y servicios de SIEMPRESOFT. | D20: S | E20: S | F20: S
A21: Miembros de la ISO/IEC | B21: Favorecer a la evolución del cambio climático. | D21: S | F21: S
B23: Leyenda | C23: Valor | D23: Puntuación | H23: Descripción | J23: Valor mínimo | K23: Obtenido
B24: P = Primario | Puede existir máximo un primario por OSI según los RyEPI | Equivale a 3 puntos | C24: 3 | D24: =COUNTIF(C4:K21,"P") -> 7 | H24: Evaluación de alineamiento de OSI con los OEEs. | J24: =(9*C24)+(80*C25) -> 107 | K24: =(D24*C24)+(D25*C25) -> 92
B25: S = Secundario | No se exige mínimo ni máximo | Equivale a 1 punto | C25: 1 | D25: =COUNTIF(C4:K21,"S") -> 71
B27: PUNTAJE | C27: =(COUNTIF(C4:C21,"S")*$C$25)+(COUNTIF(C4:C20,"P")*$C$24) -> 7 | D27: =(COUNTIF(D4:D21,"S")*$C$25)+(COUNTIF(D4:D20,"P")*$C$24) -> 17 | E27: =(COUNTIF(E4:E21,"S")*$C$25)+(COUNTIF(E4:E20,"P")*$C$24) -> 8 | F27: =(COUNTIF(F4:F21,"S")*$C$25)+(COUNTIF(F4:F20,"P")*$C$24) -> 16 | G27: =(COUNTIF(G4:G21,"S")*$C$25)+(COUNTIF(G4:G20,"P")*$C$24) -> 10 | H27: =(COUNTIF(H4:H21,"S")*$C$25)+(COUNTIF(H4:H20,"P")*$C$24) -> 8 | I27: =(COUNTIF(I4:I21,"S")*$C$25)+(COUNTIF(I4:I20,"P")*$C$24) -> 9 | J27: =(COUNTIF(J4:J21,"S")*$C$25)+(COUNTIF(J4:J20,"P")*$C$24) -> 9 | K27: =(COUNTIF(K4:K21,"S")*$C$25)+(COUNTIF(K4:K20,"P")*$C$24) -> 8
B29: Evaluación TOTAL
B30: Mínimo esperado | C30: =J24 -> 107
B31: Obtenido | C31: =SUM(C27:K27) -> 92
B32: % Representación | C32: =C31*100/C30 -> 85.981308

Sheet MEFI
A1: MATRIZ DE EVALUACIÓN DE FACTORES INTERNOS
A2: Factor crítico de éxito | B2: Clasificación
A3: FORTALEZAS
A4: Única empresa de software con PSE autorizado en Chiclayo. | B4: 4
A5: Única empresa de software en la región Lambayeque autorizado como OSE. | B5: 4
A6: Integración de servicios ERP, PSE y OSE. | B6: 4
A7: Servicio de atención de incidentes por llamadas telefónicas. | B7: 4
A8: Rentabilidad sostenible. | B8: 3
A9: Mas de 500 empresas confían en Siempresoft. | B9: 4
A10: Mas de 14 años de experiencia. | B10: 4
A11: Preparado para distintos rubros de negocios. | B11: 4
A12: Certificación internacional en Seguridad de la Información - ISO 27001. | B12: 4
A13: Servicio SAAS ofrecido en la nube 24 x 7. | B13: 3
A14: Alianzas con estudios contables | B14: 4
A15: El Acuerdo de Nivel de Servicio (SLA) superior al 99%. | B15: 3
... A17: Aplicativos multiplataforma (Android, IOS, Windows | B17: 4
A18: Subtotal FORTALEZAS | B18: =AVERAGE(B4:B17) -> 3.7857143
A19: DEBILIDADES
A20: Falta de fuerza de Ventas y Marketing. | B20: 1
A21: Falta de seguimiento a los nuevos requerimientos. | B21: 1
A22: Falta de Integración de pruebas unitarias en la fase de desarrollo | B22: 1
A23: Subtotal DEBILIDADES | B23: =AVERAGE(B20:B22) -> 1
A24: Total | B24: =B18+B23 -> 4.7857143
A26: - Clasificación: (1) Debilidad mayor | (2) Debilidad menor | (3) Fortaleza menor | (4) Fortaleza mayor
A27: - Si el total es mayor igual a 2.5, indica que la empresa presenta más fortalezas que debilidades. Si el total es menor que 2.5, indica que la empresa presenta más debilidades que fortalezas
A28: - Respecto a los subtotales, se busca que el subtotal de FORTALEZAS sea mayor al subtotal de las DEBILIDADES
A39: Consieraciones NTP ISO-IEC/31010:2017
A40: - las capacidades de la organización en términos de recursos y conocimiento,
A41: - los flujos de información y los procesos de toma de decisiones,
A42: - las partes interesadas internas,
A43: - los objetivos y las estrategias implementadas para lograrlos,
A44: - las percepciones, los valores y la cultura,
A45: - las políticas y los procesos,
A46: - las normas y los modelos de referencia adoptados por la organización, y
A47: - las estructuras (por ejemplo de gobernanza, roles y responsabilidades).

Sheet MEFE
A1: MATRIZ DE EVALUACIÓN DE FACTORES EXTERNOS
A2: Factor crítico de éxito | B2: Clasificación
A3: OPORTUNIDADES
A4: Falta de empresas PSE y OSE acreditadas por SUNAT en el departamento de Lambayeque | B4: 4
A5: Mercado en crecimiento de contribuyentes obligados a Facturación Electrónica | B5: 3
A6: Beneficio a los clientes por medio de la plataforma marketplace de Siempresoft (B2C). | B6: 2
A7: Ofrecer un B2B a los clientes. | B7: 3
A8: Prestigio y recomendación de nuestros propios clientes. | B8: 4
A9: Inteligencia artificial | B9: 3
A10: Subtotal OPORTUNIDADES | B10: =AVERAGE(B4:B9) -> 3.1666667
A11: AMENAZAS
A12: Crisis económica, política y sanitaria. | B12: 2
A13: Aumento de competencia formal e informal con precios bajos. | B13: 2
A14: Ataques informáticos al servicio en la nube, riesgos de seguridad, fuga de datos. | B14: 4
A15: Perder la acreditación PSE, OSE y certificación ISO 27001. | B15: 4
A16: Subtotal AMENAZAS | B16: =AVERAGE(B12:B15) -> 3
A17: Total | B17: =SUM(B10+B16) -> 6.1666667
A19: - Clasificación: (4) La empresa está trabajando duro | (3) La empresa trabaja más que la competencia del sector | (2) La empresa trabaja lo justo | (1) La empresa no está haciendo nada
A20: - Si el total es mayor igual a 2.5, indica que la empresa presenta más oportunidades que amenazas. Si el total es menor que 2.5, indica que la empresa presenta más amenazas que oportunidades.
A21: - Respecto a los subtotales, se busca que el subtotal de OPORTUNIDADES sea mayor al subtotal de las AMENAZAS
A32: Consieraciones NTP ISO-IEC/31010:2017
A33: - factores del entorno cultural, político, legal, reglamentario, financiero, económico y competitivo, bien sea internacional, nacional, regional o local;
A34: - tendencias y motivadores clave que tienen impacto en los objetivos de la organización; y
A35: - percepciones y valores de las partes interesadas externas.

Sheet EFIEFE
A1: MATRIZ EFI/EFE SIEMPRESOFT EIRL
B3: TOTALES PONDERADOS EFE
A4: TOTALES PONDERADOS EFI
N5: 6
N7: 5.00
C8: X
N9: 4.00
N11: 3.00
N13: 2.00
N15: 1.00
C16: 6 | E16: 5 | G16: 4.00 | I16: 3.00 | K16: 2.00 | M16: 1.00
B18: Leyenda
C19: Posición fuerte para crecer y construir
C20: Posición promedio para mantenerse
C21: Posición débil para cosechar o desinvertir
